laboro_http/__init__.py
laboro_http/schema/__init__.py
laboro_http/schema/specification.yml
laboro_http-0.0.4.dist-info/LICENSE
laboro_http-0.0.4.dist-info/METADATA
laboro_http-0.0.4.dist-info/WHEEL
laboro_http-0.0.4.dist-info/top_level.txt
laboro_http-0.0.4.dist-info/RECORD
